butch/__init__.py
butch/__main__.py
butch/caller.py
butch/charlist.py
butch/commands.py
butch/commandtype.py
butch/constants.py
butch/context.py
butch/counter.py
butch/expansion.py
butch/filmbuffer.py
butch/grammar.py
butch/inputs.py
butch/logger.py
butch/outputs.py
butch/shared.py
butch/tokenizer.py
butch/tokens.py
butch/help/<unknown>.txt
butch/help/__init__.py
butch/help/cd.txt
butch/help/cls.txt
butch/help/date.txt
butch/help/del.txt
butch/help/dir.txt
butch/help/echo.txt
butch/help/exit.txt
butch/help/mkdir.txt
butch/help/path.txt
butch/help/pause.txt
butch/help/popd.txt
butch/help/prompt.txt
butch/help/pushd.txt
butch/help/rem.txt
butch/help/rmdir.txt
butch/help/set.txt
butch/help/setlocal.txt
butch/help/time.txt
butch/help/title.txt
butch/help/type.txt
butch/tests/__init__.py
butch/tests/test.py
butch/tests/test_batchfiles.py
butch/tests/test_caller.py
butch/tests/test_charlist.py
butch/tests/test_command_cd.py
butch/tests/test_command_cls.py
butch/tests/test_command_common.py
butch/tests/test_command_date.py
butch/tests/test_command_del.py
butch/tests/test_command_dir.py
butch/tests/test_command_echo.py
butch/tests/test_command_exit.py
butch/tests/test_command_help.py
butch/tests/test_command_mkdir.py
butch/tests/test_command_path.py
butch/tests/test_command_pause.py
butch/tests/test_command_popd.py
butch/tests/test_command_prompt.py
butch/tests/test_command_pushd.py
butch/tests/test_command_rem.py
butch/tests/test_command_set.py
butch/tests/test_command_setlocal.py
butch/tests/test_command_time.py
butch/tests/test_command_type.py
butch/tests/test_command_utils.py
butch/tests/utils.py
butch/tests/batch/__init__.py
butch/tests/batch/cd_existing.bat
butch/tests/batch/cd_existing.bat.out
butch/tests/batch/cd_nonexisting.bat
butch/tests/batch/cd_nonexisting.bat.out
butch/tests/batch/delete_file.bat
butch/tests/batch/delete_file.bat.out
butch/tests/batch/delete_file_syntax.bat
butch/tests/batch/delete_file_syntax.bat.out
butch/tests/batch/delete_folder_files.bat
butch-1.0.0.dist-info/LICENSE.txt
butch-1.0.0.dist-info/METADATA
butch-1.0.0.dist-info/WHEEL
butch-1.0.0.dist-info/entry_points.txt
butch-1.0.0.dist-info/top_level.txt
butch-1.0.0.dist-info/RECORD
