Metadata-Version: 2.1
Name: butch
Version: 1.0.0
Summary: The free Batch interpreter
Home-page: https://github.com/KeyWeeUsr/Butch
Author: Peter Badida
Author-email: keyweeusr@gmail.com
License: UNKNOWN
Keywords: batch,butch,cmd,shell,interpreter,console,bat,windows,batchscript,batch-script,batchfile,batch-file,free,foss
Platform: UNKNOWN
Classifier: Development Status :: 3 - Alpha
Classifier: Environment :: Console
Classifier: Intended Audience :: Developers
Classifier: Intended Audience :: Education
Classifier: Intended Audience :: End Users/Desktop
Classifier: Intended Audience :: Information Technology
Classifier: Intended Audience :: System Administrators
Classifier: Natural Language :: English
Classifier: Natural Language :: Slovak
Classifier: Operating System :: OS Independent
Classifier: Programming Language :: Python
Classifier: Programming Language :: Python :: 3
Classifier: Programming Language :: Python :: 3 :: Only
Classifier: Programming Language :: Python :: 3.6
Classifier: Programming Language :: Python :: 3.7
Classifier: Programming Language :: Python :: 3.8
Classifier: Programming Language :: Python :: 3.9
Classifier: Programming Language :: Python :: 3.10
Classifier: Programming Language :: Python :: Implementation :: CPython
Classifier: Topic :: Software Development
Classifier: Topic :: Software Development :: Code Generators
Classifier: Topic :: Software Development :: Interpreters
Classifier: Topic :: System
Classifier: Topic :: System :: Emulators
Classifier: Topic :: System :: Shells
Classifier: Topic :: System :: System Shells
Classifier: Topic :: Terminals
Classifier: Topic :: Terminals :: Terminal Emulators/X Terminals
Classifier: Topic :: Utilities
Classifier: Typing :: Typed
Requires-Python: >=3.6
License-File: LICENSE.txt
Provides-Extra: dev
Requires-Dist: coverage (>=5.5) ; extra == 'dev'
Requires-Dist: pycodestyle (>=2.7.0) ; extra == 'dev'
Requires-Dist: pylint (>=2.9.3) ; extra == 'dev'
Requires-Dist: wemake-python-styleguide (>=0.15.3) ; extra == 'dev'
Provides-Extra: release
Requires-Dist: setuptools ; extra == 'release'
Requires-Dist: wheel ; extra == 'release'
Requires-Dist: twine ; extra == 'release'
Requires-Dist: readme-renderer ; extra == 'release'
